odoo/addons/sale_coupon_reward_add_product/README.rst
odoo/addons/sale_coupon_reward_add_product/__init__.py
odoo/addons/sale_coupon_reward_add_product/__manifest__.py
odoo/addons/sale_coupon_reward_add_product/i18n/it.po
odoo/addons/sale_coupon_reward_add_product/i18n/sale_coupon_reward_add_product.pot
odoo/addons/sale_coupon_reward_add_product/models/__init__.py
odoo/addons/sale_coupon_reward_add_product/models/coupon_coupon.py
odoo/addons/sale_coupon_reward_add_product/models/coupon_program.py
odoo/addons/sale_coupon_reward_add_product/models/coupon_reward.py
odoo/addons/sale_coupon_reward_add_product/models/sale_order.py
odoo/addons/sale_coupon_reward_add_product/readme/CONFIGURE.rst
odoo/addons/sale_coupon_reward_add_product/readme/CONTRIBUTORS.rst
odoo/addons/sale_coupon_reward_add_product/readme/DESCRIPTION.rst
odoo/addons/sale_coupon_reward_add_product/static/description/icon.png
odoo/addons/sale_coupon_reward_add_product/static/description/index.html
odoo/addons/sale_coupon_reward_add_product/tests/__init__.py
odoo/addons/sale_coupon_reward_add_product/tests/test_sale.py
odoo/addons/sale_coupon_reward_add_product/views/coupon_program.xml
odoo14_addon_sale_coupon_reward_add_product-14.0.1.0.1.dev7.dist-info/METADATA
odoo14_addon_sale_coupon_reward_add_product-14.0.1.0.1.dev7.dist-info/WHEEL
odoo14_addon_sale_coupon_reward_add_product-14.0.1.0.1.dev7.dist-info/top_level.txt
odoo14_addon_sale_coupon_reward_add_product-14.0.1.0.1.dev7.dist-info/RECORD
